{"col":6,"value":"1","tb":{"col":-1,"results":{"1":81}},"fb":{"col":0,"value":"112","tb":{"col":7,"value":"1","tb":{"col":11,"value":"0.0993","tb":{"col":0,"value":"164","tb":{"col":10,"value":"1429390.25","tb":{"col":11,"value":"0.3253","tb":{"col":11,"value":"0.4313","tb":{"col":-1,"results":{"0":1}},"fb":{"col":-1,"results":{"1":4}}},"fb":{"col":4,"value":"1","tb":{"col":-1,"results":{"0":6}},"fb":{"col":2,"value":"1","tb":{"col":-1,"results":{"1":2}},"fb":{"col":10,"value":"6721023","tb":{"col":10,"value":"74000000","tb":{"col":-1,"results":{"0":3}},"fb":{"col":0,"value":"184","tb":{"col":10,"value":"9592613","tb":{"col":0,"value":"2104","tb":{"col":-1,"results":{"1":1}},"fb":{"col":10,"value":"60522118","tb":{"col":-1,"results":{"1":1}},"fb":{"col":7,"value":"2","tb":{"col":11,"value":"0.1072","tb":{"col":11,"value":"0.1204","tb":{"col":10,"value":"49680000","tb":{"col":-1,"results":{"0":2}},"fb":{"col":11,"value":"0.1373","tb":{"col":7,"value":"8","tb":{"col":9,"value":"8","tb":{"col":-1,"results":{"0":1}},"fb":{"col":-1,"results":{"1":2}}},"fb":{"col":-1,"results":{"0":3}}},"fb":{"col":-1,"results":{"1":3}}}},"fb":{"col":-1,"results":{"0":5}}},"fb":{"col":-1,"results":{"1":1}}},"fb":{"col":-1,"results":{"0":5}}}}},"fb":{"col":0,"value":"328","tb":{"col":-1,"results":{"0":2}},"fb":{"col":-1,"results":{"1":4}}}},"fb":{"col":1,"value":"11-50","tb":{"col":-1,"results":{"0":1}},"fb":{"col":-1,"results":{"1":4}}}}},"fb":{"col":11,"value":"0.1823","tb":{"col":-1,"results":{"0":8}},"fb":{"col":11,"value":"0.1608","tb":{"col":-1,"results":{"1":2}},"fb":{"col":11,"value":"0.1024","tb":{"col":10,"value":"4920000","tb":{"col":-1,"results":{"0":6}},"fb":{"col":0,"value":"292","tb":{"col":-1,"results":{"1":1}},"fb":{"col":0,"value":"192","tb":{"col":-1,"results":{"0":4}},"fb":{"col":0,"value":"184","tb":{"col":-1,"results":{"1":1}},"fb":{"col":-1,"results":{"0":2}}}}}},"fb":{"col":-1,"results":{"1":1}}}}}}}}},"fb":{"col":-1,"results":{"0":7}}},"fb":{"col":10,"value":"15000000","tb":{"col":-1,"results":{"0":21}},"fb":{"col":7,"value":"7","tb":{"col":-1,"results":{"0":10}},"fb":{"col":10,"value":"3200000","tb":{"col":10,"value":"7283333.333","tb":{"col":10,"value":"14700000","tb":{"col":-1,"results":{"1":1}},"fb":{"col":11,"value":"0.2361","tb":{"col":-1,"results":{"0":11}},"fb":{"col":7,"value":"3","tb":{"col":9,"value":"2","tb":{"col":7,"value":"5","tb":{"col":0,"value":"136","tb":{"col":-1,"results":{"0":3}},"fb":{"col":-1,"results":{"1":1}}},"fb":{"col":-1,"results":{"1":3}}},"fb":{"col":-1,"results":{"0":4}}},"fb":{"col":-1,"results":{"0":8}}}}},"fb":{"col":4,"value":"3","tb":{"col":-1,"results":{"1":2}},"fb":{"col":11,"value":"0.1225","tb":{"col":10,"value":"4840000","tb":{"col":11,"value":"0.14","tb":{"col":10,"value":"6881650","tb":{"col":-1,"results":{"1":2}},"fb":{"col":10,"value":"6472155.667","tb":{"col":-1,"results":{"0":3}},"fb":{"col":10,"value":"5900000","tb":{"col":-1,"results":{"1":4}},"fb":{"col":11,"value":"0.1662","tb":{"col":11,"value":"0.2662","tb":{"col":-1,"results":{"1":1}},"fb":{"col":-1,"results":{"0":3}}},"fb":{"col":-1,"results":{"1":2}}}}}},"fb":{"col":-1,"results":{"0":3}}},"fb":{"col":-1,"results":{"0":6}}},"fb":{"col":-1,"results":{"1":2}}}}},"fb":{"col":11,"value":"0.1546","tb":{"col":-1,"results":{"0":18}},"fb":{"col":0,"value":"145","tb":{"col":-1,"results":{"0":6}},"fb":{"col":0,"value":"116","tb":{"col":11,"value":"0.1339","tb":{"col":-1,"results":{"1":4}},"fb":{"col":7,"value":"3","tb":{"col":-1,"results":{"0":4}},"fb":{"col":7,"value":"2","tb":{"col":10,"value":"1400000","tb":{"col":11,"value":"0.1197","tb":{"col":-1,"results":{"0":1}},"fb":{"col":-1,"results":{"1":2}}},"fb":{"col":-1,"results":{"0":2}}},"fb":{"col":-1,"results":{"1":1}}}}},"fb":{"col":-1,"results":{"0":6}}}}}}}}},"fb":{"col":11,"value":"0.0839","tb":{"col":-1,"results":{"0":23}},"fb":{"col":11,"value":"0.0833","tb":{"col":-1,"results":{"1":2}},"fb":{"col":-1,"results":{"0":20}}}}},"fb":{"col":-1,"results":{"0":26}}},"fb":{"col":0,"value":"70","tb":{"col":11,"value":"0.1865","tb":{"col":11,"value":"0.1877","tb":{"col":0,"value":"71","tb":{"col":5,"value":"1","tb":{"col":-1,"results":{"1":1}},"fb":{"col":7,"value":"4","tb":{"col":-1,"results":{"0":23}},"fb":{"col":7,"value":"1","tb":{"col":10,"value":"8250000","tb":{"col":-1,"results":{"0":5}},"fb":{"col":10,"value":"4750000","tb":{"col":-1,"results":{"1":1}},"fb":{"col":1,"value":"","tb":{"col":0,"value":"100","tb":{"col":-1,"results":{"0":3}},"fb":{"col":10,"value":"3000000","tb":{"col":-1,"results":{"0":1}},"fb":{"col":-1,"results":{"1":2}}}},"fb":{"col":-1,"results":{"0":5}}}}},"fb":{"col":-1,"results":{"0":8}}}}},"fb":{"col":-1,"results":{"1":1}}},"fb":{"col":-1,"results":{"1":2}}},"fb":{"col":11,"value":"0.1394","tb":{"col":-1,"results":{"0":41}},"fb":{"col":11,"value":"0.1335","tb":{"col":0,"value":"101","tb":{"col":-1,"results":{"0":2}},"fb":{"col":7,"value":"3","tb":{"col":-1,"results":{"0":1}},"fb":{"col":-1,"results":{"1":2}}}},"fb":{"col":-1,"results":{"0":36}}}}},"fb":{"col":10,"value":"1300000","tb":{"col":10,"value":"1655000","tb":{"col":2,"value":"1","tb":{"col":11,"value":"0.2588","tb":{"col":-1,"results":{"0":8}},"fb":{"col":0,"value":"64","tb":{"col":-1,"results":{"0":1}},"fb":{"col":-1,"results":{"1":1}}}},"fb":{"col":-1,"results":{"0":95}}},"fb":{"col":10,"value":"1617252","tb":{"col":-1,"results":{"1":1}},"fb":{"col":7,"value":"7","tb":{"col":0,"value":"64","tb":{"col":-1,"results":{"0":1}},"fb":{"col":-1,"results":{"1":1}}},"fb":{"col":-1,"results":{"0":12}}}}},"fb":{"col":-1,"results":{"0":207}}}}}}